{
	"name": "Logging",
	"index_last_check": 0,
	"last_update": 1624440302,
	"libraries": [
		{
			"id": 13628513,
			"name": "logrus",
			"description": "Structured, pluggable logging for Go.",
			"html_url": "https://github.com/sirupsen/logrus",
			"homepage": "",
			"created_at": "2013-10-16T19:08:55Z",
			"updated_at": "2021-06-23T08:41:11Z",
			"svn_url": "https://github.com/sirupsen/logrus",
			"stargazers_count": 18080,
			"watchers_count": 18080,
			"forks_count": 1961,
			"open_issues_count": 119
		},
		{
			"id": 52034309,
			"name": "zap",
			"description": "Blazing fast, structured, leveled logging in Go.",
			"html_url": "https://github.com/uber-go/zap",
			"homepage": "https://godoc.org/go.uber.org/zap",
			"created_at": "2016-02-18T19:52:56Z",
			"updated_at": "2021-06-23T07:41:52Z",
			"svn_url": "https://github.com/uber-go/zap",
			"stargazers_count": 12885,
			"watchers_count": 12885,
			"forks_count": 972,
			"open_issues_count": 90
		},
		{
			"id": 91054480,
			"name": "zerolog",
			"description": "Zero Allocation JSON Logger",
			"html_url": "https://github.com/rs/zerolog",
			"homepage": "",
			"created_at": "2017-05-12T05:24:39Z",
			"updated_at": "2021-06-23T07:36:33Z",
			"svn_url": "https://github.com/rs/zerolog",
			"stargazers_count": 4825,
			"watchers_count": 4825,
			"forks_count": 292,
			"open_issues_count": 68
		},
		{
			"id": 7515336,
			"name": "go-spew",
			"description": "Implements a deep pretty printer for Go data structures to aid in debugging",
			"html_url": "https://github.com/davecgh/go-spew",
			"homepage": "",
			"created_at": "2013-01-09T05:18:22Z",
			"updated_at": "2021-06-22T17:51:21Z",
			"svn_url": "https://github.com/davecgh/go-spew",
			"stargazers_count": 4465,
			"watchers_count": 4465,
			"forks_count": 290,
			"open_issues_count": 55
		},
		{
			"id": 11440704,
			"name": "glog",
			"description": "Leveled execution logs for Go",
			"html_url": "https://github.com/golang/glog",
			"homepage": "",
			"created_at": "2013-07-16T04:33:04Z",
			"updated_at": "2021-06-21T14:24:36Z",
			"svn_url": "https://github.com/golang/glog",
			"stargazers_count": 2734,
			"watchers_count": 2734,
			"forks_count": 774,
			"open_issues_count": 8
		},
		{
			"id": 20831114,
			"name": "lumberjack",
			"description": "lumberjack is a log rolling package for Go",
			"html_url": "https://github.com/natefinch/lumberjack",
			"homepage": "",
			"created_at": "2014-06-14T11:55:47Z",
			"updated_at": "2021-06-23T07:51:36Z",
			"svn_url": "https://github.com/natefinch/lumberjack",
			"stargazers_count": 2596,
			"watchers_count": 2596,
			"forks_count": 348,
			"open_issues_count": 51
		},
		{
			"id": 8019413,
			"name": "tail",
			"description": "Go package for reading from continously updated files (tail -f)",
			"html_url": "https://github.com/hpcloud/tail",
			"homepage": "",
			"created_at": "2013-02-05T00:28:03Z",
			"updated_at": "2021-06-22T13:10:10Z",
			"svn_url": "https://github.com/hpcloud/tail",
			"stargazers_count": 2117,
			"watchers_count": 2117,
			"forks_count": 426,
			"open_issues_count": 70
		},
		{
			"id": 2794417,
			"name": "seelog",
			"description": "Seelog is a native Go logging library that provides flexible asynchronous dispatching, filtering, and formatting.",
			"html_url": "https://github.com/cihub/seelog",
			"homepage": "",
			"created_at": "2011-11-17T09:43:15Z",
			"updated_at": "2021-06-20T03:57:09Z",
			"svn_url": "https://github.com/cihub/seelog",
			"stargazers_count": 1543,
			"watchers_count": 1543,
			"forks_count": 242,
			"open_issues_count": 39
		},
		{
			"id": 48392478,
			"name": "log",
			"description": "Structured logging package for Go.",
			"html_url": "https://github.com/apex/log",
			"homepage": "",
			"created_at": "2015-12-21T20:27:48Z",
			"updated_at": "2021-06-21T08:08:33Z",
			"svn_url": "https://github.com/apex/log",
			"stargazers_count": 1144,
			"watchers_count": 1144,
			"forks_count": 95,
			"open_issues_count": 34
		},
		{
			"id": 19961931,
			"name": "log15",
			"description": "Structured, composable logging for Go",
			"html_url": "https://github.com/inconshreveable/log15",
			"homepage": "https://godoc.org/github.com/inconshreveable/log15",
			"created_at": "2014-05-20T00:11:52Z",
			"updated_at": "2021-06-21T08:08:28Z",
			"svn_url": "https://github.com/inconshreveable/log15",
			"stargazers_count": 1012,
			"watchers_count": 1012,
			"forks_count": 137,
			"open_issues_count": 43
		},
		{
			"id": 132346526,
			"name": "onelog",
			"description": "Dead simple, super fast, zero allocation and modular logger for Golang",
			"html_url": "https://github.com/francoispqt/onelog",
			"homepage": "",
			"created_at": "2018-05-06T14:32:10Z",
			"updated_at": "2021-06-12T08:42:40Z",
			"svn_url": "https://github.com/francoispqt/onelog",
			"stargazers_count": 394,
			"watchers_count": 394,
			"forks_count": 14,
			"open_issues_count": 1
		},
		{
			"id": 195634128,
			"name": "log",
			"description": "Structured Logging Made Easy",
			"html_url": "https://github.com/phuslu/log",
			"homepage": "",
			"created_at": "2019-07-07T09:40:38Z",
			"updated_at": "2021-06-22T18:09:50Z",
			"svn_url": "https://github.com/phuslu/log",
			"stargazers_count": 375,
			"watchers_count": 375,
			"forks_count": 23,
			"open_issues_count": 3
		},
		{
			"id": 31512899,
			"name": "logxi",
			"description": "A 12-factor app logger built for performance and happy development",
			"html_url": "https://github.com/mgutz/logxi",
			"homepage": "https://logur.dev/logur",
			"created_at": "2015-03-01T22:13:45Z",
			"updated_at": "2021-05-08T17:22:18Z",
			"svn_url": "https://github.com/mgutz/logxi",
			"stargazers_count": 347,
			"watchers_count": 347,
			"forks_count": 39,
			"open_issues_count": 24
		},
		{
			"id": 13435885,
			"name": "logutils",
			"description": "Utilities for slightly better logging in Go (Golang).",
			"html_url": "https://github.com/hashicorp/logutils",
			"homepage": "https://logur.dev/logur",
			"created_at": "2013-10-09T07:31:15Z",
			"updated_at": "2021-03-24T13:59:46Z",
			"svn_url": "https://github.com/hashicorp/logutils",
			"stargazers_count": 292,
			"watchers_count": 292,
			"forks_count": 31,
			"open_issues_count": 1
		},
		{
			"id": 51254271,
			"name": "log",
			"description": ":green_book: Simple, configurable and scalable Structured Logging for Go.",
			"html_url": "https://github.com/go-playground/log",
			"homepage": "",
			"created_at": "2016-02-07T16:17:48Z",
			"updated_at": "2021-05-06T17:20:44Z",
			"svn_url": "https://github.com/go-playground/log",
			"stargazers_count": 275,
			"watchers_count": 275,
			"forks_count": 21,
			"open_issues_count": 1
		},
		{
			"id": 24486800,
			"name": "go-logger",
			"description": "Simple logger for Go programs. Allows custom formats for messages.",
			"html_url": "https://github.com/apsdehal/go-logger",
			"homepage": "",
			"created_at": "2014-09-26T04:57:06Z",
			"updated_at": "2021-06-18T03:21:21Z",
			"svn_url": "https://github.com/apsdehal/go-logger",
			"stargazers_count": 263,
			"watchers_count": 263,
			"forks_count": 49,
			"open_issues_count": 2
		},
		{
			"id": 236057614,
			"name": "httpretty",
			"description": "Package httpretty prints the HTTP requests you make with Go pretty on your terminal.",
			"html_url": "https://github.com/henvic/httpretty",
			"homepage": "https://asciinema.org/a/297429",
			"created_at": "2020-01-24T18:17:16Z",
			"updated_at": "2021-06-10T04:17:21Z",
			"svn_url": "https://github.com/henvic/httpretty",
			"stargazers_count": 228,
			"watchers_count": 228,
			"forks_count": 6,
			"open_issues_count": 1
		},
		{
			"id": 219189025,
			"name": "sqldb-logger",
			"description": "A logger for Go SQL database driver without modify existing *sql.DB stdlib usage.",
			"html_url": "https://github.com/simukti/sqldb-logger",
			"homepage": "",
			"created_at": "2019-11-02T17:28:03Z",
			"updated_at": "2021-06-13T10:47:37Z",
			"svn_url": "https://github.com/simukti/sqldb-logger",
			"stargazers_count": 180,
			"watchers_count": 180,
			"forks_count": 5,
			"open_issues_count": 4
		},
		{
			"id": 81722987,
			"name": "rollingwriter",
			"description": "Rolling writer is an IO util for auto rolling write in go.",
			"html_url": "https://github.com/arthurkiller/rollingwriter",
			"homepage": "",
			"created_at": "2017-02-12T12:05:26Z",
			"updated_at": "2021-06-20T14:26:49Z",
			"svn_url": "https://github.com/arthurkiller/rollingwriter",
			"stargazers_count": 176,
			"watchers_count": 176,
			"forks_count": 26,
			"open_issues_count": 8
		},
		{
			"id": 24627405,
			"name": "logger",
			"description": "Minimalistic logging library for Go.",
			"html_url": "https://github.com/azer/logger",
			"homepage": "http://godoc.org/github.com/azer/logger",
			"created_at": "2014-09-30T06:45:09Z",
			"updated_at": "2021-03-29T21:01:13Z",
			"svn_url": "https://github.com/azer/logger",
			"stargazers_count": 148,
			"watchers_count": 148,
			"forks_count": 15,
			"open_issues_count": 0
		},
		{
			"id": 44735328,
			"name": "xlog",
			"description": "xlog is a logger for net/context aware HTTP applications",
			"html_url": "https://github.com/rs/xlog",
			"homepage": "",
			"created_at": "2015-10-22T09:26:45Z",
			"updated_at": "2021-02-20T02:54:42Z",
			"svn_url": "https://github.com/rs/xlog",
			"stargazers_count": 135,
			"watchers_count": 135,
			"forks_count": 12,
			"open_issues_count": 3
		},
		{
			"id": 161060081,
			"name": "logur",
			"description": "Logur is an opinionated collection of logging best practices",
			"html_url": "https://github.com/logur/logur",
			"homepage": "https://logur.dev/logur",
			"created_at": "2018-12-09T16:43:11Z",
			"updated_at": "2021-06-10T16:44:50Z",
			"svn_url": "https://github.com/logur/logur",
			"stargazers_count": 126,
			"watchers_count": 126,
			"forks_count": 8,
			"open_issues_count": 8
		},
		{
			"id": 95006858,
			"name": "glg",
			"description": "Simple and blazing fast lockfree logging library for golang",
			"html_url": "https://github.com/kpango/glg",
			"homepage": "",
			"created_at": "2017-06-21T13:26:16Z",
			"updated_at": "2021-06-19T04:03:48Z",
			"svn_url": "https://github.com/kpango/glg",
			"stargazers_count": 114,
			"watchers_count": 114,
			"forks_count": 11,
			"open_issues_count": 1
		},
		{
			"id": 44776974,
			"name": "ozzo-log",
			"description": "A Go (golang) package providing high-performance asynchronous logging, message filtering by severity and category, and multiple message targets.",
			"html_url": "https://github.com/go-ozzo/ozzo-log",
			"homepage": "",
			"created_at": "2015-10-22T22:29:02Z",
			"updated_at": "2021-05-17T07:01:57Z",
			"svn_url": "https://github.com/go-ozzo/ozzo-log",
			"stargazers_count": 114,
			"watchers_count": 114,
			"forks_count": 31,
			"open_issues_count": 9
		},
		{
			"id": 33070003,
			"name": "logvoyage",
			"description": "LogVoyage - logging SaaS written in GoLang",
			"html_url": "https://github.com/firstrow/logvoyage",
			"homepage": "",
			"created_at": "2015-03-29T11:05:09Z",
			"updated_at": "2020-09-04T14:11:03Z",
			"svn_url": "https://github.com/firstrow/logvoyage",
			"stargazers_count": 88,
			"watchers_count": 88,
			"forks_count": 10,
			"open_issues_count": 9
		},
		{
			"id": 18942887,
			"name": "log",
			"description": "Logging packages for Go",
			"html_url": "https://github.com/alexcesaro/log",
			"homepage": "",
			"created_at": "2014-04-19T14:31:56Z",
			"updated_at": "2020-08-12T17:36:34Z",
			"svn_url": "https://github.com/alexcesaro/log",
			"stargazers_count": 45,
			"watchers_count": 45,
			"forks_count": 3,
			"open_issues_count": 1
		},
		{
			"id": 80907602,
			"name": "go-cronowriter",
			"description": "Time based rotating file writer",
			"html_url": "https://github.com/utahta/go-cronowriter",
			"homepage": "",
			"created_at": "2017-02-04T09:02:55Z",
			"updated_at": "2021-05-31T11:45:51Z",
			"svn_url": "https://github.com/utahta/go-cronowriter",
			"stargazers_count": 41,
			"watchers_count": 41,
			"forks_count": 7,
			"open_issues_count": 3
		},
		{
			"id": 41790658,
			"name": "gologger",
			"description": "The Simplest and worst logging library ever written",
			"html_url": "https://github.com/sadlil/gologger",
			"homepage": "",
			"created_at": "2015-09-02T08:52:26Z",
			"updated_at": "2021-01-19T03:46:18Z",
			"svn_url": "https://github.com/sadlil/gologger",
			"stargazers_count": 39,
			"watchers_count": 39,
			"forks_count": 10,
			"open_issues_count": 2
		},
		{
			"id": 25023596,
			"name": "logex",
			"description": "An golang log lib, supports tracking and level, wrap by standard log lib",
			"html_url": "https://github.com/chzyer/logex",
			"homepage": "",
			"created_at": "2014-10-10T06:38:39Z",
			"updated_at": "2021-03-29T21:33:46Z",
			"svn_url": "https://github.com/chzyer/logex",
			"stargazers_count": 37,
			"watchers_count": 37,
			"forks_count": 8,
			"open_issues_count": 2
		},
		{
			"id": 19361990,
			"name": "go-log",
			"description": "A logger, for Go",
			"html_url": "https://github.com/ian-kent/go-log",
			"homepage": "",
			"created_at": "2014-05-02T00:34:09Z",
			"updated_at": "2021-02-21T19:02:39Z",
			"svn_url": "https://github.com/ian-kent/go-log",
			"stargazers_count": 37,
			"watchers_count": 37,
			"forks_count": 17,
			"open_issues_count": 3
		},
		{
			"id": 67408014,
			"name": "gone",
			"description": "Golang packages for writing small daemons and servers.",
			"html_url": "https://github.com/One-com/gone",
			"homepage": "",
			"created_at": "2016-09-05T09:39:11Z",
			"updated_at": "2021-05-24T14:22:10Z",
			"svn_url": "https://github.com/One-com/gone",
			"stargazers_count": 35,
			"watchers_count": 35,
			"forks_count": 5,
			"open_issues_count": 0
		},
		{
			"id": 19902156,
			"name": "go-log",
			"description": "a golang log lib supports level and multi handlers",
			"html_url": "https://github.com/siddontang/go-log",
			"homepage": "",
			"created_at": "2014-05-18T03:41:55Z",
			"updated_at": "2020-11-11T08:54:54Z",
			"svn_url": "https://github.com/siddontang/go-log",
			"stargazers_count": 28,
			"watchers_count": 28,
			"forks_count": 14,
			"open_issues_count": 1
		},
		{
			"id": 101149056,
			"name": "journald",
			"description": "Go implementation of systemd Journal's native API for logging",
			"html_url": "https://github.com/ssgreg/journald",
			"homepage": "https://asciinema.org/a/297429",
			"created_at": "2017-08-23T07:06:09Z",
			"updated_at": "2021-03-05T18:33:49Z",
			"svn_url": "https://github.com/ssgreg/journald",
			"stargazers_count": 26,
			"watchers_count": 26,
			"forks_count": 1,
			"open_issues_count": 0
		},
		{
			"id": 23939547,
			"name": "logrusly",
			"description": "Loggly Hooks for GO Logrus logger",
			"html_url": "https://github.com/sebest/logrusly",
			"homepage": "",
			"created_at": "2014-09-11T23:27:11Z",
			"updated_at": "2020-08-17T21:36:09Z",
			"svn_url": "https://github.com/sebest/logrusly",
			"stargazers_count": 26,
			"watchers_count": 26,
			"forks_count": 14,
			"open_issues_count": 2
		},
		{
			"id": 44119979,
			"name": "distillog",
			"description": "Logging, distilled",
			"html_url": "https://github.com/amoghe/distillog",
			"homepage": "",
			"created_at": "2015-10-12T16:32:21Z",
			"updated_at": "2021-06-21T15:05:58Z",
			"svn_url": "https://github.com/amoghe/distillog",
			"stargazers_count": 26,
			"watchers_count": 26,
			"forks_count": 5,
			"open_issues_count": 0
		},
		{
			"id": 108679849,
			"name": "log",
			"description": "Structured log interface",
			"html_url": "https://github.com/teris-io/log",
			"homepage": "",
			"created_at": "2017-10-28T19:57:55Z",
			"updated_at": "2021-01-03T07:59:28Z",
			"svn_url": "https://github.com/teris-io/log",
			"stargazers_count": 24,
			"watchers_count": 24,
			"forks_count": 2,
			"open_issues_count": 0
		},
		{
			"id": 25471841,
			"name": "mlog",
			"description": "A simple logging module for go, with a rotating file feature and console logging.",
			"html_url": "https://github.com/jbrodriguez/mlog",
			"homepage": "",
			"created_at": "2014-10-20T15:06:26Z",
			"updated_at": "2021-03-21T07:13:54Z",
			"svn_url": "https://github.com/jbrodriguez/mlog",
			"stargazers_count": 23,
			"watchers_count": 23,
			"forks_count": 17,
			"open_issues_count": 1
		},
		{
			"id": 41634108,
			"name": "gomol",
			"description": "Gomol is a library for structured, multiple-output logging for Go with extensible logging outputs",
			"html_url": "https://github.com/aphistic/gomol",
			"homepage": "",
			"created_at": "2015-08-30T15:51:46Z",
			"updated_at": "2021-04-21T04:52:21Z",
			"svn_url": "https://github.com/aphistic/gomol",
			"stargazers_count": 17,
			"watchers_count": 17,
			"forks_count": 0,
			"open_issues_count": 3
		},
		{
			"id": 251626501,
			"name": "zkits-logger",
			"description": "A powerful zero-dependency json logger.",
			"html_url": "https://github.com/edoger/zkits-logger",
			"homepage": "",
			"created_at": "2020-03-31T14:23:40Z",
			"updated_at": "2021-06-17T03:37:04Z",
			"svn_url": "https://github.com/edoger/zkits-logger",
			"stargazers_count": 15,
			"watchers_count": 15,
			"forks_count": 0,
			"open_issues_count": 0
		},
		{
			"id": 166598763,
			"name": "glo",
			"description": "Logging library for Golang",
			"html_url": "https://github.com/lajosbencz/glo",
			"homepage": "",
			"created_at": "2019-01-19T22:10:42Z",
			"updated_at": "2021-06-04T05:15:29Z",
			"svn_url": "https://github.com/lajosbencz/glo",
			"stargazers_count": 14,
			"watchers_count": 14,
			"forks_count": 0,
			"open_issues_count": 0
		},
		{
			"id": 201430966,
			"name": "logrusiowriter",
			"description": "io.Writer implementation using logrus logger",
			"html_url": "https://github.com/cabify/logrusiowriter",
			"homepage": "",
			"created_at": "2019-08-09T08:58:25Z",
			"updated_at": "2021-04-28T10:20:48Z",
			"svn_url": "https://github.com/cabify/logrusiowriter",
			"stargazers_count": 12,
			"watchers_count": 12,
			"forks_count": 0,
			"open_issues_count": 0
		},
		{
			"id": 90518012,
			"name": "go-log",
			"description": "Simple and configurable Logging in Go, with level, formatters and writers",
			"html_url": "https://github.com/subchen/go-log",
			"homepage": "",
			"created_at": "2017-05-07T08:09:24Z",
			"updated_at": "2021-02-21T03:47:33Z",
			"svn_url": "https://github.com/subchen/go-log",
			"stargazers_count": 11,
			"watchers_count": 11,
			"forks_count": 5,
			"open_issues_count": 0
		},
		{
			"id": 156475181,
			"name": "logmatic",
			"description": "Colorized logger for Golang with dynamic log level configuration",
			"html_url": "https://github.com/mborders/logmatic",
			"homepage": "http://godoc.org/github.com/azer/logger",
			"created_at": "2018-11-07T01:52:45Z",
			"updated_at": "2021-03-10T18:40:34Z",
			"svn_url": "https://github.com/mborders/logmatic",
			"stargazers_count": 10,
			"watchers_count": 10,
			"forks_count": 3,
			"open_issues_count": 1
		},
		{
			"id": 78861795,
			"name": "logdump",
			"description": "Package for multi-level logging",
			"html_url": "https://github.com/ewwwwwqm/logdump",
			"homepage": "",
			"created_at": "2017-01-13T15:34:31Z",
			"updated_at": "2019-07-22T17:02:07Z",
			"svn_url": "https://github.com/ewwwwwqm/logdump",
			"stargazers_count": 9,
			"watchers_count": 9,
			"forks_count": 2,
			"open_issues_count": 0
		},
		{
			"id": 81237818,
			"name": "logo",
			"description": "Golang logger to different configurable writers.",
			"html_url": "https://github.com/mbndr/logo",
			"homepage": "",
			"created_at": "2017-02-07T18:02:55Z",
			"updated_at": "2021-02-09T06:29:03Z",
			"svn_url": "https://github.com/mbndr/logo",
			"stargazers_count": 9,
			"watchers_count": 9,
			"forks_count": 1,
			"open_issues_count": 0
		},
		{
			"id": 93930453,
			"name": "log",
			"description": ":memo: Logging with multiple output targets.",
			"html_url": "https://github.com/aerogo/log",
			"homepage": "",
			"created_at": "2017-06-10T09:54:08Z",
			"updated_at": "2020-11-19T15:43:56Z",
			"svn_url": "https://github.com/aerogo/log",
			"stargazers_count": 8,
			"watchers_count": 8,
			"forks_count": 0,
			"open_issues_count": 0
		},
		{
			"id": 212052071,
			"name": "go-log",
			"description": "A logging library with strack traces, object dumping and optional timestamps",
			"html_url": "https://github.com/pieterclaerhout/go-log",
			"homepage": "",
			"created_at": "2019-10-01T08:55:38Z",
			"updated_at": "2021-02-21T07:39:35Z",
			"svn_url": "https://github.com/pieterclaerhout/go-log",
			"stargazers_count": 8,
			"watchers_count": 8,
			"forks_count": 3,
			"open_issues_count": 0
		},
		{
			"id": 58146351,
			"name": "xlog",
			"description": "plugin architecture and flexible log system for golang",
			"html_url": "https://github.com/xfxdev/xlog",
			"homepage": "",
			"created_at": "2016-05-05T16:47:45Z",
			"updated_at": "2019-09-26T11:33:58Z",
			"svn_url": "https://github.com/xfxdev/xlog",
			"stargazers_count": 6,
			"watchers_count": 6,
			"forks_count": 3,
			"open_issues_count": 0
		},
		{
			"id": 279197216,
			"name": "kemba",
			"description": "A tiny debug logging tool. Ideal for CLI tools and command applications. Inspired by https://github.com/visionmedia/debug",
			"html_url": "https://github.com/clok/kemba",
			"homepage": "https://pkg.go.dev/github.com/clok/kemba?tab=overview",
			"created_at": "2020-07-13T03:10:54Z",
			"updated_at": "2021-05-21T04:32:04Z",
			"svn_url": "https://github.com/clok/kemba",
			"stargazers_count": 5,
			"watchers_count": 5,
			"forks_count": 1,
			"open_issues_count": 0
		},
		{
			"id": 336828640,
			"name": "yell",
			"description": "Yet another minimalistic logging library",
			"html_url": "https://github.com/jfcg/yell",
			"homepage": "",
			"created_at": "2021-02-07T16:07:27Z",
			"updated_at": "2021-05-21T13:00:39Z",
			"svn_url": "https://github.com/jfcg/yell",
			"stargazers_count": 1,
			"watchers_count": 1,
			"forks_count": 0,
			"open_issues_count": 0
		}
	]
}